torch_llm_kernels/__init__.py
torch_llm_kernels/csrc/kernels.h
torch_llm_kernels/csrc/module.cpp
torch_llm_kernels/csrc/swiglu_kernel.cu
torch_llm_kernels/ops/__init__.py
torch_llm_kernels/ops/swiglu.py
torch_llm_kernels-0.1.0.dist-info/licenses/LICENSE
torch_llm_kernels-0.1.0.dist-info/METADATA
torch_llm_kernels-0.1.0.dist-info/WHEEL
torch_llm_kernels-0.1.0.dist-info/top_level.txt
torch_llm_kernels-0.1.0.dist-info/RECORD
