Metadata-Version: 2.4
Name: torch-llm-kernels
Version: 0.1.0
Summary: CUDA Kernels for Large Language Models (LLMs), compatible with torch.compile.
Author-email: AI-Infra-Core <ai.infra.core@gmail.com>
License-Expression: MIT
Project-URL: Homepage, https://github.com/AI-Infra-Core/torch-llm-kernels
Project-URL: Bug Tracker, https://github.com/AI-Infra-Core/torch-llm-kernels/issues
Classifier: Development Status :: 4 - Beta
Classifier: Intended Audience :: Developers
Classifier: Operating System :: OS Independent
Classifier: Programming Language :: Python :: 3.8
Classifier: Programming Language :: Python :: 3.9
Classifier: Programming Language :: Python :: 3.10
Classifier: Programming Language :: Python :: 3.11
Classifier: Topic :: Scientific/Engineering :: Artificial Intelligence
Requires-Python: >=3.9
License-File: LICENSE
Requires-Dist: torch>=2.6
Provides-Extra: test
Requires-Dist: pytest; extra == "test"
Dynamic: license-file
